mysqlbuilder/Builder.py
mysqlbuilder/__init__.py
tests/Test.py
tests/__init__.py
mysqlbuilder-1.1.1.dist-info/LICENSE
mysqlbuilder-1.1.1.dist-info/METADATA
mysqlbuilder-1.1.1.dist-info/WHEEL
mysqlbuilder-1.1.1.dist-info/top_level.txt
mysqlbuilder-1.1.1.dist-info/RECORD
