Metadata-Version: 2.1
Name: mysqlbuilder
Version: 1.1.1
Summary: This is a simple python mysql builder design to easiy query & get data from your mysql database
Home-page: https://github.com/Dip20/mysqlbuilder
Author: Santu Sarkar
Author-email: santusarkar2020@gmail.com
License-File: LICENSE
